[
  {
    "description": "    As a user I want to visit the detail page\n    So I can provide my correct details",
    "keyword": "Feature",
    "name": "Visit Your Detail page",
    "line": 1,
    "id": "visit-your-detail-page",
    "tags": [],
    "uri": "YourDetailsPage.feature",
    "elements": [
      {
        "id": "visit-your-detail-page;your-detail-page-displays-for-single-journey",
        "keyword": "Scenario",
        "line": 6,
        "name": "Your Detail Page displays for single journey",
        "tags": [
          {
            "name": "@automating",
            "line": 5
          }
        ],
        "type": "scenario",
        "steps": [
          {
            "arguments": [],
            "keyword": "Given ",
            "line": 7,
            "name": "I am a user of ForSea",
            "result": {
              "status": "passed",
              "duration": 801000000
            }
          },
          {
            "arguments": [],
            "keyword": "When ",
            "line": 8,
            "name": "I am on Book your journey page",
            "result": {
              "status": "passed",
              "duration": 3962000000
            }
          },
          {
            "arguments": [],
            "keyword": "And ",
            "line": 9,
            "name": "'Route' section is completed",
            "result": {
              "status": "passed",
              "duration": 26799000000
            }
          },
          {
            "arguments": [],
            "keyword": "And ",
            "line": 10,
            "name": "'How' section is completed",
            "result": {
              "status": "passed",
              "duration": 23636000000
            }
          },
          {
            "arguments": [],
            "keyword": "And ",
            "line": 11,
            "name": "'The OutBound' section is completed",
            "result": {
              "status": "passed",
              "duration": 27447000000
            }
          },
          {
            "arguments": [],
            "keyword": "When ",
            "line": 12,
            "name": "'DONE' button is selected",
            "result": {
              "status": "passed",
              "duration": 872000000
            }
          },
          {
            "arguments": [],
            "keyword": "Then ",
            "line": 13,
            "name": "'YOUR DETAILS' page displays",
            "result": {
              "status": "passed",
              "duration": 796000000
            }
          },
          {
            "arguments": [],
            "keyword": "And ",
            "line": 14,
            "name": "'Booking Summary' section matches booking information",
            "result": {
              "status": "passed",
              "duration": 6436000000
            }
          }
        ]
      },
      {
        "id": "visit-your-detail-page;your-detail-page-displays-for-return-journey",
        "keyword": "Scenario",
        "line": 17,
        "name": "Your Detail Page displays for return journey",
        "tags": [
          {
            "name": "@automating",
            "line": 16
          }
        ],
        "type": "scenario",
        "steps": [
          {
            "arguments": [],
            "keyword": "Given ",
            "line": 18,
            "name": "I am a user of ForSea",
            "result": {
              "status": "passed",
              "duration": 5680000000
            }
          },
          {
            "arguments": [],
            "keyword": "When ",
            "line": 19,
            "name": "I am on Book your journey page",
            "result": {
              "status": "passed",
              "duration": 1870000000
            }
          },
          {
            "arguments": [],
            "keyword": "And ",
            "line": 20,
            "name": "'Route' section is completed",
            "result": {
              "status": "passed",
              "duration": 29649000000
            }
          },
          {
            "arguments": [],
            "keyword": "And ",
            "line": 21,
            "name": "'How' section is completed",
            "result": {
              "status": "passed",
              "duration": 32838000000
            }
          },
          {
            "arguments": [],
            "keyword": "And ",
            "line": 22,
            "name": "'The OutBound' section is completed",
            "result": {
              "status": "passed",
              "duration": 38070000000
            }
          },
          {
            "arguments": [],
            "keyword": "And ",
            "line": 23,
            "name": "'Return' section is completed",
            "result": {
              "status": "passed",
              "duration": 47423000000
            }
          },
          {
            "arguments": [],
            "keyword": "When ",
            "line": 24,
            "name": "'DONE' button is selected",
            "result": {
              "status": "passed",
              "duration": 2248000000
            }
          },
          {
            "arguments": [],
            "keyword": "Then ",
            "line": 25,
            "name": "'YOUR DETAILS' page displays",
            "result": {
              "status": "passed",
              "duration": 2644000000
            }
          },
          {
            "arguments": [],
            "keyword": "And ",
            "line": 26,
            "name": "'Booking Summary' section matches booking information for round trip",
            "result": {
              "status": "passed",
              "duration": 41702000000
            }
          }
        ]
      },
      {
        "id": "visit-your-detail-page;your-detail-page-contains-six-text-boxes",
        "keyword": "Scenario",
        "line": 40,
        "name": "Your Detail Page contains six text boxes",
        "tags": [
          {
            "name": "@automating",
            "line": 28
          }
        ],
        "type": "scenario",
        "steps": [
          {
            "arguments": [],
            "keyword": "Given ",
            "line": 30,
            "name": "I am a user of ForSea",
            "result": {
              "status": "passed",
              "duration": 1183000000
            }
          },
          {
            "arguments": [],
            "keyword": "When ",
            "line": 31,
            "name": "I am on Book your journey page",
            "result": {
              "status": "passed",
              "duration": 1347000000
            }
          },
          {
            "arguments": [],
            "keyword": "And ",
            "line": 32,
            "name": "'Route' section is completed",
            "result": {
              "status": "passed",
              "duration": 22640000000
            }
          },
          {
            "arguments": [],
            "keyword": "And ",
            "line": 33,
            "name": "'How' section is completed",
            "result": {
              "status": "passed",
              "duration": 19601000000
            }
          },
          {
            "arguments": [],
            "keyword": "And ",
            "line": 34,
            "name": "'The OutBound' section is completed",
            "result": {
              "status": "passed",
              "duration": 34802000000
            }
          },
          {
            "arguments": [],
            "keyword": "When ",
            "line": 35,
            "name": "'DONE' button is selected",
            "result": {
              "status": "passed",
              "duration": 1275000000
            }
          },
          {
            "arguments": [],
            "keyword": "Then ",
            "line": 36,
            "name": "'YOUR DETAILS' page displays with six '<Text>' boxes",
            "result": {
              "status": "passed",
              "duration": 13578000000
            }
          }
        ]
      },
      {
        "id": "visit-your-detail-page;your-detail-page-contains-two-checkboxes",
        "keyword": "Scenario",
        "line": 54,
        "name": "Your Detail Page contains two checkboxes",
        "tags": [
          {
            "name": "@automating",
            "line": 42
          }
        ],
        "type": "scenario",
        "steps": [
          {
            "arguments": [],
            "keyword": "Given ",
            "line": 44,
            "name": "I am a user of ForSea",
            "result": {
              "status": "passed",
              "duration": 1004000000
            }
          },
          {
            "arguments": [],
            "keyword": "When ",
            "line": 45,
            "name": "I am on Book your journey page",
            "result": {
              "status": "passed",
              "duration": 1211000000
            }
          },
          {
            "arguments": [],
            "keyword": "And ",
            "line": 46,
            "name": "'Route' section is completed",
            "result": {
              "status": "passed",
              "duration": 25401000000
            }
          },
          {
            "arguments": [],
            "keyword": "And ",
            "line": 47,
            "name": "'How' section is completed",
            "result": {
              "status": "passed",
              "duration": 23270000000
            }
          },
          {
            "arguments": [],
            "keyword": "And ",
            "line": 48,
            "name": "'The OutBound' section is completed",
            "result": {
              "status": "passed",
              "duration": 36335000000
            }
          },
          {
            "arguments": [],
            "keyword": "When ",
            "line": 49,
            "name": "'DONE' button is selected",
            "result": {
              "status": "passed",
              "duration": 684000000
            }
          },
          {
            "arguments": [],
            "keyword": "Then ",
            "line": 50,
            "name": "'YOUR DETAILS' page displays with two <check boxes>",
            "result": {
              "status": "passed",
              "duration": 10250000000
            }
          }
        ]
      },
      {
        "id": "visit-your-detail-page;make-payment-button-is-highlighted-when-text-boxes-is-not-filled",
        "keyword": "Scenario",
        "line": 57,
        "name": "Make Payment button is highlighted when text boxes is not filled",
        "tags": [
          {
            "name": "@automating",
            "line": 56
          }
        ],
        "type": "scenario",
        "steps": [
          {
            "arguments": [],
            "keyword": "Given ",
            "line": 58,
            "name": "I am a user of ForSea",
            "result": {
              "status": "passed",
              "duration": 918000000
            }
          },
          {
            "arguments": [],
            "keyword": "When ",
            "line": 59,
            "name": "I am on Book your journey page",
            "result": {
              "status": "passed",
              "duration": 1124000000
            }
          },
          {
            "arguments": [],
            "keyword": "And ",
            "line": 60,
            "name": "'Route' section is completed",
            "result": {
              "status": "passed",
              "duration": 17787000000
            }
          },
          {
            "arguments": [],
            "keyword": "And ",
            "line": 61,
            "name": "'How' section is completed",
            "result": {
              "status": "passed",
              "duration": 27129000000
            }
          },
          {
            "arguments": [],
            "keyword": "And ",
            "line": 62,
            "name": "'The OutBound' section is completed",
            "result": {
              "status": "passed",
              "duration": 26278000000
            }
          },
          {
            "arguments": [],
            "keyword": "When ",
            "line": 63,
            "name": "'DONE' button is selected",
            "result": {
              "status": "passed",
              "duration": 677000000
            }
          },
          {
            "arguments": [],
            "keyword": "Then ",
            "line": 64,
            "name": "'YOUR DETAILS' page displays",
            "result": {
              "status": "passed",
              "duration": 1018000000
            }
          },
          {
            "arguments": [],
            "keyword": "And ",
            "line": 65,
            "name": "'Make Payment' button is highlighted in red",
            "result": {
              "status": "passed",
              "duration": 9262000000
            }
          }
        ]
      },
      {
        "id": "visit-your-detail-page;error-message-displays-when-a-field-is-in-focus",
        "keyword": "Scenario",
        "line": 68,
        "name": "Error message displays when a field is in focus",
        "tags": [
          {
            "name": "@automating",
            "line": 67
          }
        ],
        "type": "scenario",
        "steps": [
          {
            "arguments": [],
            "keyword": "Given ",
            "line": 69,
            "name": "I am a user of ForSea",
            "result": {
              "status": "passed",
              "duration": 1780000000
            }
          },
          {
            "arguments": [],
            "keyword": "When ",
            "line": 70,
            "name": "I am on Book your journey page",
            "result": {
              "status": "passed",
              "duration": 1187000000
            }
          },
          {
            "arguments": [],
            "keyword": "And ",
            "line": 71,
            "name": "'Route' section is completed",
            "result": {
              "status": "passed",
              "duration": 19916000000
            }
          },
          {
            "arguments": [],
            "keyword": "And ",
            "line": 72,
            "name": "'How' section is completed",
            "result": {
              "status": "passed",
              "duration": 17263000000
            }
          },
          {
            "arguments": [],
            "keyword": "And ",
            "line": 73,
            "name": "'The OutBound' section is completed",
            "result": {
              "status": "passed",
              "duration": 30615000000
            }
          },
          {
            "arguments": [],
            "keyword": "When ",
            "line": 74,
            "name": "'DONE' button is selected",
            "result": {
              "status": "passed",
              "duration": 735000000
            }
          },
          {
            "arguments": [],
            "keyword": "Then ",
            "line": 75,
            "name": "'YOUR DETAILS' page displays",
            "result": {
              "status": "passed",
              "duration": 872000000
            }
          },
          {
            "arguments": [],
            "keyword": "When ",
            "line": 76,
            "name": "I click inside a 'Text Box' and clcik in the next input the '* Required field' message is displayed",
            "result": {
              "status": "passed",
              "duration": 17850000000
            }
          }
        ]
      },
      {
        "id": "visit-your-detail-page;error-message-displays-when-wrong-information-is-entered-in-phone-field",
        "keyword": "Scenario",
        "line": 93,
        "name": "Error message displays when wrong information is entered in Phone field",
        "tags": [
          {
            "name": "@automating",
            "line": 78
          }
        ],
        "type": "scenario",
        "steps": [
          {
            "arguments": [],
            "keyword": "Given ",
            "line": 80,
            "name": "I am a user of ForSea",
            "result": {
              "status": "passed",
              "duration": 702000000
            }
          },
          {
            "arguments": [],
            "keyword": "When ",
            "line": 81,
            "name": "I am on Book your journey page",
            "result": {
              "status": "passed",
              "duration": 1157000000
            }
          },
          {
            "arguments": [],
            "keyword": "And ",
            "line": 82,
            "name": "'Route' section is completed",
            "result": {
              "status": "passed",
              "duration": 20541000000
            }
          },
          {
            "arguments": [],
            "keyword": "And ",
            "line": 83,
            "name": "'How' section is completed",
            "result": {
              "status": "passed",
              "duration": 21735000000
            }
          },
          {
            "arguments": [],
            "keyword": "And ",
            "line": 84,
            "name": "'The OutBound' section is completed",
            "result": {
              "status": "passed",
              "duration": 31434000000
            }
          },
          {
            "arguments": [],
            "keyword": "When ",
            "line": 85,
            "name": "'DONE' button is selected",
            "result": {
              "status": "passed",
              "duration": 988000000
            }
          },
          {
            "arguments": [],
            "keyword": "Then ",
            "line": 86,
            "name": "'YOUR DETAILS' page displays",
            "result": {
              "status": "passed",
              "duration": 937000000
            }
          },
          {
            "arguments": [],
            "keyword": "When ",
            "line": 87,
            "name": "I enter \"@@@###$$$\" in \"Phone number\" field text Box",
            "result": {
              "status": "passed",
              "duration": 19142000000
            }
          },
          {
            "arguments": [],
            "keyword": "And ",
            "line": 88,
            "name": "I tick 'I approve ForSea Ferries terms and conditions and privacy policy' Checkbox",
            "result": {
              "status": "passed",
              "duration": 1933000000
            }
          },
          {
            "arguments": [],
            "keyword": "Then ",
            "line": 89,
            "name": "'Please fill in the required items' message is displayed",
            "result": {
              "status": "passed",
              "duration": 981000000
            }
          }
        ]
      },
      {
        "id": "visit-your-detail-page;error-message-displays-when-wrong-information-is-entered-in-email-field",
        "keyword": "Scenario",
        "line": 111,
        "name": "Error message displays when wrong information is entered in Email field",
        "tags": [
          {
            "name": "@automating",
            "line": 96
          }
        ],
        "type": "scenario",
        "steps": [
          {
            "arguments": [],
            "keyword": "Given ",
            "line": 98,
            "name": "I am a user of ForSea",
            "result": {
              "status": "passed",
              "duration": 883000000
            }
          },
          {
            "arguments": [],
            "keyword": "When ",
            "line": 99,
            "name": "I am on Book your journey page",
            "result": {
              "status": "passed",
              "duration": 1965000000
            }
          },
          {
            "arguments": [],
            "keyword": "And ",
            "line": 100,
            "name": "'Route' section is completed",
            "result": {
              "status": "passed",
              "duration": 25437000000
            }
          },
          {
            "arguments": [],
            "keyword": "And ",
            "line": 101,
            "name": "'How' section is completed",
            "result": {
              "status": "passed",
              "duration": 21421000000
            }
          },
          {
            "arguments": [],
            "keyword": "And ",
            "line": 102,
            "name": "'The OutBound' section is completed",
            "result": {
              "status": "passed",
              "duration": 33592000000
            }
          },
          {
            "arguments": [],
            "keyword": "When ",
            "line": 103,
            "name": "'DONE' button is selected",
            "result": {
              "status": "passed",
              "duration": 961000000
            }
          },
          {
            "arguments": [],
            "keyword": "Then ",
            "line": 104,
            "name": "'YOUR DETAILS' page displays",
            "result": {
              "status": "passed",
              "duration": 861000000
            }
          },
          {
            "arguments": [],
            "keyword": "When ",
            "line": 105,
            "name": "I enter \"@@@###$$$\" in \"Email\" field text Box",
            "result": {
              "status": "passed",
              "duration": 7882000000
            }
          },
          {
            "arguments": [],
            "keyword": "And ",
            "line": 106,
            "name": "I tick 'I approve ForSea Ferries terms and conditions and privacy policy' Checkbox",
            "result": {
              "status": "passed",
              "duration": 1839000000
            }
          },
          {
            "arguments": [],
            "keyword": "Then ",
            "line": 107,
            "name": "'Please fill in the required items' message is displayed",
            "result": {
              "status": "passed",
              "duration": 970000000
            }
          }
        ]
      },
      {
        "id": "visit-your-detail-page;error-message-displays-when-wrong-information-is-entered-in-confirm-email-field",
        "keyword": "Scenario",
        "line": 128,
        "name": "Error message displays when wrong information is entered in Confirm Email field",
        "tags": [
          {
            "name": "@automating",
            "line": 113
          }
        ],
        "type": "scenario",
        "steps": [
          {
            "arguments": [],
            "keyword": "Given ",
            "line": 115,
            "name": "I am a user of ForSea",
            "result": {
              "status": "passed",
              "duration": 902000000
            }
          },
          {
            "arguments": [],
            "keyword": "When ",
            "line": 116,
            "name": "I am on Book your journey page",
            "result": {
              "status": "passed",
              "duration": 942000000
            }
          },
          {
            "arguments": [],
            "keyword": "And ",
            "line": 117,
            "name": "'Route' section is completed",
            "result": {
              "status": "passed",
              "duration": 40873000000
            }
          },
          {
            "arguments": [],
            "keyword": "And ",
            "line": 118,
            "name": "'How' section is completed",
            "result": {
              "status": "passed",
              "duration": 28595000000
            }
          },
          {
            "arguments": [],
            "keyword": "And ",
            "line": 119,
            "name": "'The OutBound' section is completed",
            "result": {
              "status": "passed",
              "duration": 27111000000
            }
          },
          {
            "arguments": [],
            "keyword": "When ",
            "line": 120,
            "name": "'DONE' button is selected",
            "result": {
              "status": "passed",
              "duration": 1323000000
            }
          },
          {
            "arguments": [],
            "keyword": "Then ",
            "line": 121,
            "name": "'YOUR DETAILS' page displays",
            "result": {
              "status": "passed",
              "duration": 1504000000
            }
          },
          {
            "arguments": [],
            "keyword": "When ",
            "line": 122,
            "name": "I enter \"@@@###$$$\" in \"Confirm Email\" field text Box",
            "result": {
              "status": "passed",
              "duration": 12211000000
            }
          },
          {
            "arguments": [],
            "keyword": "And ",
            "line": 123,
            "name": "I tick 'I approve ForSea Ferries terms and conditions and privacy policy' Checkbox",
            "result": {
              "status": "passed",
              "duration": 1862000000
            }
          },
          {
            "arguments": [],
            "keyword": "Then ",
            "line": 124,
            "name": "'Please fill in the required items' message is displayed",
            "result": {
              "status": "passed",
              "duration": 1733000000
            }
          }
        ]
      },
      {
        "id": "visit-your-detail-page;error-message-displays-when-wrong-information-is-entered-in-first-name-field",
        "keyword": "Scenario",
        "line": 145,
        "name": "Error message displays when wrong information is entered in First name field",
        "tags": [
          {
            "name": "@automating",
            "line": 130
          }
        ],
        "type": "scenario",
        "steps": [
          {
            "arguments": [],
            "keyword": "Given ",
            "line": 132,
            "name": "I am a user of ForSea",
            "result": {
              "status": "passed",
              "duration": 834000000
            }
          },
          {
            "arguments": [],
            "keyword": "When ",
            "line": 133,
            "name": "I am on Book your journey page",
            "result": {
              "status": "passed",
              "duration": 1246000000
            }
          },
          {
            "arguments": [],
            "keyword": "And ",
            "line": 134,
            "name": "'Route' section is completed",
            "result": {
              "status": "passed",
              "duration": 18446000000
            }
          },
          {
            "arguments": [],
            "keyword": "And ",
            "line": 135,
            "name": "'How' section is completed",
            "result": {
              "status": "passed",
              "duration": 19494000000
            }
          },
          {
            "arguments": [],
            "keyword": "And ",
            "line": 136,
            "name": "'The OutBound' section is completed",
            "result": {
              "status": "passed",
              "duration": 31097000000
            }
          },
          {
            "arguments": [],
            "keyword": "When ",
            "line": 137,
            "name": "'DONE' button is selected",
            "result": {
              "status": "passed",
              "duration": 2413000000
            }
          },
          {
            "arguments": [],
            "keyword": "Then ",
            "line": 138,
            "name": "'YOUR DETAILS' page displays",
            "result": {
              "status": "passed",
              "duration": 4378000000
            }
          },
          {
            "arguments": [],
            "keyword": "When ",
            "line": 139,
            "name": "I enter \"123456789\" in \"First name\" field text Box",
            "result": {
              "status": "passed",
              "duration": 25265000000
            }
          },
          {
            "arguments": [],
            "keyword": "And ",
            "line": 140,
            "name": "I tick 'I approve ForSea Ferries terms and conditions and privacy policy' Checkbox",
            "result": {
              "status": "passed",
              "duration": 4840000000
            }
          },
          {
            "arguments": [],
            "keyword": "Then ",
            "line": 141,
            "name": "'Please fill in the required items' message is displayed",
            "result": {
              "status": "passed",
              "duration": 2200000000
            }
          }
        ]
      },
      {
        "id": "visit-your-detail-page;error-message-displays-when-wrong-information-is-entered-in-last-name-field",
        "keyword": "Scenario",
        "line": 162,
        "name": "Error message displays when wrong information is entered in Last name field",
        "tags": [
          {
            "name": "@automating",
            "line": 147
          }
        ],
        "type": "scenario",
        "steps": [
          {
            "arguments": [],
            "keyword": "Given ",
            "line": 149,
            "name": "I am a user of ForSea",
            "result": {
              "status": "passed",
              "duration": 2413000000
            }
          },
          {
            "arguments": [],
            "keyword": "When ",
            "line": 150,
            "name": "I am on Book your journey page",
            "result": {
              "status": "passed",
              "duration": 1408000000
            }
          },
          {
            "arguments": [],
            "keyword": "And ",
            "line": 151,
            "name": "'Route' section is completed",
            "result": {
              "status": "passed",
              "duration": 25304000000
            }
          },
          {
            "arguments": [],
            "keyword": "And ",
            "line": 152,
            "name": "'How' section is completed",
            "result": {
              "status": "passed",
              "duration": 25614000000
            }
          },
          {
            "arguments": [],
            "keyword": "And ",
            "line": 153,
            "name": "'The OutBound' section is completed",
            "result": {
              "status": "passed",
              "duration": 40666000000
            }
          },
          {
            "arguments": [],
            "keyword": "When ",
            "line": 154,
            "name": "'DONE' button is selected",
            "result": {
              "status": "passed",
              "duration": 1436000000
            }
          },
          {
            "arguments": [],
            "keyword": "Then ",
            "line": 155,
            "name": "'YOUR DETAILS' page displays",
            "result": {
              "status": "passed",
              "duration": 1295000000
            }
          },
          {
            "arguments": [],
            "keyword": "When ",
            "line": 156,
            "name": "I enter \"123456789\" in \"Last name\" field text Box",
            "result": {
              "status": "passed",
              "duration": 18075000000
            }
          },
          {
            "arguments": [],
            "keyword": "And ",
            "line": 157,
            "name": "I tick 'I approve ForSea Ferries terms and conditions and privacy policy' Checkbox",
            "result": {
              "status": "passed",
              "duration": 4819000000
            }
          },
          {
            "arguments": [],
            "keyword": "Then ",
            "line": 158,
            "name": "'Please fill in the required items' message is displayed",
            "result": {
              "status": "passed",
              "duration": 2817000000
            }
          }
        ]
      }
    ]
  }
]